<?xml version="1.0" encoding="utf-8"?>
<!--_MODULUS=rZ5o7cs5mdFTrd1gdndCHiZ4MS9P6jLCAtrhRWcKZgb+PSUJV2KBjGd53dvgUx2rfAJD5EO4zcbQqmni9zVQmlq/4SSK+wTyHM98aXz7IAMGzERJu3PQbKCeRrX5JQzUGhcI3EFNCo2VgaIFtTOiDe3txiTeS0c1mfIgWu10ZIo=-->
<!--_SIG=ZZPiwtP9ZPvszkH3hJUukLZ7BmCPOODLPNoSFG0QpXzDtj02nEaAkV+xe+MAYTXW5ZTvfw4YV82go5Wgm0IRinvr55cJhLXEM04sCaDFpJrXrHl6R4GUl9y2m0VuQd1fnzNdp0lgiFQvanI33WwNJYCHc7YcYCpyQnWJns1r7xE=-->
<Setup Id="Outlook.pt-br" Type="AddOn" Keyword="OutlookMUI" Culture="pt-br">
	<Option Id="AlwaysInstalled" DefaultState="Local" DisallowAbsent="yes" DisallowAdvertise="yes" Hidden="yes"/>
	<Option Id="Gimme_OnDemandData" DefaultState="Local" DisallowAbsent="yes" DisallowAdvertise="yes" Hidden="yes"/>
	<Option Id="ProductFiles" DefaultState="Local" DisallowAbsent="yes" DisallowAdvertise="no">
		<Option Id="OUTLOOKFiles" DefaultState="Local" DisallowAbsent="no" DisallowAdvertise="no">
			<Option Id="OutlookHelpFiles" DefaultState="FollowParent" DisallowAbsent="yes" DisallowAdvertise="no" Hidden="yes"/>
			<Option Id="OutlookImportExportFiles" DefaultState="Local" DisallowAbsent="no" DisallowAdvertise="no">
				<Option Id="OutlookDVExtensionsFiles" DefaultState="Local" DisallowAbsent="no" DisallowAdvertise="no">
					<Option Id="OutlookDVCsvWinFiles" DefaultState="Local" DisallowAbsent="no" DisallowAdvertise="no"/>
				</Option>
			</Option>
			<Option Id="OutlookStationeryFiles" DefaultState="Local" DisallowAbsent="no" DisallowAdvertise="no">
				<Option Id="OutlookStationeryBasicFiles" DefaultState="Local" DisallowAbsent="no" DisallowAdvertise="no"/>
				<Option Id="OutlookStationeryExtended" DefaultState="Local" DisallowAbsent="no" DisallowAdvertise="no"/>
			</Option>
			<Option Id="OutlookTemplateFiles" DefaultState="Absent" DisallowAbsent="no" DisallowAdvertise="yes"/>
			<Option Id="OutlookMessaging" DefaultState="Local" DisallowAbsent="yes" DisallowAdvertise="no">
				<OptionDependency Lead="OUTLOOKFiles"/>
				<Option Id="OutlookMAPI2" DefaultState="Local" DisallowAbsent="yes" DisallowAdvertise="no">
					<OptionDependency Lead="OUTLOOKFiles"/>
				</Option>
			</Option>
			<Option Id="OutlookAddIns" DefaultState="Local" DisallowAbsent="no" DisallowAdvertise="yes">
				<Option Id="OutlookSocialConnector" DefaultState="Local" DisallowAbsent="no" DisallowAdvertise="yes"/>
			</Option>
			<Option Id="OutlookOms" DefaultState="FollowParent" DisallowAbsent="yes" DisallowAdvertise="no" Hidden="yes"/>
		</Option>
		<Option Id="OutlookSearchShellRegIntl" DefaultState="Local" DisallowAbsent="no" DisallowAdvertise="yes" Hidden="yes">
			<OptionDependency Lead="OUTLOOKFiles"/>
		</Option>
		<Option Id="WORDSharedFiles" DefaultState="Absent" DisallowAbsent="no" DisallowAdvertise="no" Hidden="yes">
			<OptionDependency Lead="OUTLOOKFiles"/>
			<OptionDependency Lead="WORDFiles"/>
		</Option>
		<Option Id="WhiteRabbitHidden" DefaultState="Absent" DisallowAbsent="no" DisallowAdvertise="yes" Hidden="yes">
			<OptionDependency Lead="WORDFiles"/>
			<OptionDependency Lead="EXCELFiles"/>
			<OptionDependency Lead="OUTLOOKFiles"/>
		</Option>
	</Option>
	<PackageRef Path="OutlookMUI.xml"/>
	<LocalCache DownloadCode="{90150000-001A-0416-0000-0000000FF1CE}" SkuComponentDirectory="Outlook.pt-br">
		<File Id="OutlookMUI.xml" MD5="87EE2EC36115928FCF60BB8B757F8395" Size="0" RelativeCachePath="OutlookMUI.xml" RelativeSourcePath="OutlookMUI.xml"/>
		<File Id="OutlookMUI.msi" MD5="4DA756E5E8680B568391D77DC1A7B0F8" Size="2101248" RelativeCachePath="OutlookMUI.msi" RelativeSourcePath="OutlookMUI.msi"/>
		<File Id="OutlkLR.cab" MD5="0DD7C1F45E3C00E62696A91D3CDB1AF6" Size="3365333" RelativeCachePath="OutlkLR.cab" RelativeSourcePath="OutlkLR.cab"/>
		<File Id="Setup.xml" MD5="" Size="" RelativeCachePath="Setup.xml" RelativeSourcePath="Setup.xml"/>
	</LocalCache>
</Setup>
